amazon_page_parser/VERSION
amazon_page_parser/__init__.py
amazon_page_parser/parsers.py
amazon_page_parser/tracking_parser.py
amazon_page_parser-0.1.4.dist-info/METADATA
amazon_page_parser-0.1.4.dist-info/WHEEL
amazon_page_parser-0.1.4.dist-info/top_level.txt
amazon_page_parser-0.1.4.dist-info/RECORD
